openanalysis
