Metadata-Version: 1.1
Name: OpenAnalysis
Version: 0.0.6
Summary: An open source package to analyse and visualise algorithms and data structures
Home-page: https://github.com/OpenWeavers/OpenAlgorithm
Author: OpenWeavers1
Author-email: srmonish96@gmail.com
License: GPLv3+
Keywords: OpenWeavers product
Platform: UNKNOWN
Classifier: Development Status :: 3 - Alpha
Classifier: Topic :: Software Development :: Libraries :: Python Modules
Classifier: Programming Language :: Python :: 3.5
Classifier: Intended Audience :: Developers
Classifier: License :: OSI Approved :: GNU General Public License v3 or later (GPLv3+)
